bnflow/__init__.py
bnflow/__version__.py
brainnetworkflow-0.0.1.dist-info/METADATA
brainnetworkflow-0.0.1.dist-info/WHEEL
brainnetworkflow-0.0.1.dist-info/top_level.txt
brainnetworkflow-0.0.1.dist-info/RECORD
