Metadata-Version: 2.4
Name: brainnetworkflow
Version: 0.0.1
Summary: Brain network graph analysis and simulation toolkit.
Author: Lantix-Lab
Classifier: Programming Language :: Python :: 3
Classifier: License :: OSI Approved :: MIT License
Classifier: Operating System :: OS Independent
Requires-Python: >=3.10
